diffwofost/__init__.py
diffwofost/physical_models/__init__.py
diffwofost/physical_models/config.py
diffwofost/physical_models/engine.py
diffwofost/physical_models/utils.py
diffwofost/physical_models/crop/__init__.py
diffwofost/physical_models/crop/assimilation.py
diffwofost/physical_models/crop/leaf_dynamics.py
diffwofost/physical_models/crop/partitioning.py
diffwofost/physical_models/crop/phenology.py
diffwofost/physical_models/crop/root_dynamics.py
diffwofost-0.3.0.dist-info/licenses/LICENSE
diffwofost-0.3.0.dist-info/METADATA
diffwofost-0.3.0.dist-info/WHEEL
diffwofost-0.3.0.dist-info/top_level.txt
diffwofost-0.3.0.dist-info/RECORD
