Metadata-Version: 2.4
Name: diffwofost
Version: 0.3.0
Summary: Differentiable WOFOST
Author: Francesco Nattino, Ron van Bree
Author-email: Sarah Alidoost <f.alidoost@esciencecenter.nl>, Michiel Kallenberg <michiel.kallenberg@wur.nl>
License: **EUPL, Version 1.1**
Project-URL: Repository, https://github.com/WUR-AI/diffwofost
Project-URL: Issues, https://github.com/WUR-AI/diffwofost/issues
Keywords: wofost,pytorch,differentiable,crop,optimization
Classifier: Development Status :: 2 - Pre-Alpha
Classifier: Intended Audience :: Developers
Classifier: Intended Audience :: Science/Research
Classifier: Natural Language :: English
Classifier: Programming Language :: Python :: 3
Classifier: Programming Language :: Python :: 3.11
Classifier: Programming Language :: Python :: 3.12
Classifier: Programming Language :: Python :: 3.13
Requires-Python: >=3.11
License-File: LICENSE
Requires-Dist: torch
Requires-Dist: pcse
Provides-Extra: dev
Requires-Dist: pytest; extra == "dev"
Requires-Dist: pytest-cov; extra == "dev"
Requires-Dist: ruff; extra == "dev"
Requires-Dist: mypy; extra == "dev"
Requires-Dist: pre-commit; extra == "dev"
Provides-Extra: docs
Requires-Dist: mkdocs; extra == "docs"
Requires-Dist: mkdocs-material; extra == "docs"
Requires-Dist: mkdocs-jupyter; extra == "docs"
Requires-Dist: mkdocstrings[python]>=0.18; extra == "docs"
Requires-Dist: mkdocs-gen-files; extra == "docs"
Requires-Dist: mkdocs-include-markdown-plugin; extra == "docs"
Requires-Dist: jupyterlab; extra == "docs"
Requires-Dist: matplotlib; extra == "docs"
Dynamic: license-file
